odoo/addons/project_timeline_critical_path/README.rst
odoo/addons/project_timeline_critical_path/__init__.py
odoo/addons/project_timeline_critical_path/__manifest__.py
odoo/addons/project_timeline_critical_path/i18n/de.po
odoo/addons/project_timeline_critical_path/i18n/project_timeline_critical_path.pot
odoo/addons/project_timeline_critical_path/models/__init__.py
odoo/addons/project_timeline_critical_path/models/project_project.py
odoo/addons/project_timeline_critical_path/models/project_task.py
odoo/addons/project_timeline_critical_path/models/res_company.py
odoo/addons/project_timeline_critical_path/models/res_config_settings.py
odoo/addons/project_timeline_critical_path/readme/CONFIGURE.rst
odoo/addons/project_timeline_critical_path/readme/CONTRIBUTORS.rst
odoo/addons/project_timeline_critical_path/readme/DESCRIPTION.rst
odoo/addons/project_timeline_critical_path/readme/INSTALL.rst
odoo/addons/project_timeline_critical_path/readme/ROADMAP.rst
odoo/addons/project_timeline_critical_path/readme/USAGE.rst
odoo/addons/project_timeline_critical_path/static/description/icon.png
odoo/addons/project_timeline_critical_path/static/description/index.html
odoo/addons/project_timeline_critical_path/static/description/screenshot.png
odoo/addons/project_timeline_critical_path/static/src/js/backend.js
odoo/addons/project_timeline_critical_path/templates/assets.xml
odoo/addons/project_timeline_critical_path/tests/__init__.py
odoo/addons/project_timeline_critical_path/tests/test_critical_path.py
odoo/addons/project_timeline_critical_path/views/res_config_settings_view.xml
odoo11_addon_project_timeline_critical_path-11.0.1.0.0.99.dev11.dist-info/METADATA
odoo11_addon_project_timeline_critical_path-11.0.1.0.0.99.dev11.dist-info/WHEEL
odoo11_addon_project_timeline_critical_path-11.0.1.0.0.99.dev11.dist-info/top_level.txt
odoo11_addon_project_timeline_critical_path-11.0.1.0.0.99.dev11.dist-info/RECORD
